[{"name":"lubiao_b0","position":[0,0.06,0.1],"rotation":[0,0,0,-1]},{"name":"lubiao_a0","position":[0.25,0.06,0.1],"rotation":[0,0,0,-1]},{"name":"lubiao_c0","position":[-0.25,0.06,0.1],"rotation":[0,0,0,-1]},{"name":"Road_03","position":[0,0,0],"rotation":[0,0,0,-1]},{"name":"End_01","position":[0,0,0],"rotation":[0,0,0,-1]},{"name":"Water","position":[0,-4.54,0],"rotation":[0,0,0,-1]},{"name":"Road_01","position":[0,0,-0.5],"rotation":[0,0,0,-1]},{"name":"lubiao_c1_cm7","position":[-0.25,0.06,-1],"rotation":[0,0,0,-1]},{"name":"Road_01","position":[0,0,-1],"rotation":[0,0,0,-1]},{"name":"lubiao_a1_cm7","position":[0.25,0.06,-1],"rotation":[0,0,0,-1]},{"name":"lubiao_b1_cm7","position":[0,0.06,-1],"rotation":[0,0,0,-1]},{"name":"Road_01","position":[0,0,-1.5],"rotation":[0,0,0,-1]},{"name":"Machine_07","position":[0,1.72,-1.572],"rotation":[0,1,0,0]},{"name":"Road_01","position":[0,0,-2],"rotation":[0,0,0,-1]},{"name":"Road_01","position":[0,0,-2.5],"rotation":[0,0,0,-1]},{"name":"Road_01","position":[0,0,-3],"rotation":[0,0,0,-1]},{"name":"Road_01","position":[0,0,-3.5],"rotation":[0,0,0,-1]},{"name":"Road_01","position":[0,0,-4],"rotation":[0,0,0,-1]},{"name":"Road_01","position":[0,0,-4.5],"rotation":[0,0,0,-1]},{"name":"Road_01","position":[0,0,-5],"rotation":[0,0,0,-1]},{"name":"Road_01","position":[0,0,-5.5],"rotation":[0,0,0,-1]},{"name":"Road_01","position":[0,0,-6],"rotation":[0,0,0,-1]},{"name":"Road_01","position":[0,0,-6.5],"rotation":[0,0,0,-1]},{"name":"Road_01","position":[0,0,-7],"rotation":[0,0,0,-1]},{"name":"Road_01","position":[0,0,-7.5],"rotation":[0,0,0,-1]},{"name":"Road_01","position":[0,0,-8],"rotation":[0,0,0,-1]},{"name":"Road_01","position":[0,0,-8.5],"rotation":[0,0,0,-1]},{"name":"Road_01","position":[0,0,-9],"rotation":[0,0,0,-1]},{"name":"lubiao_a2_c020_r5p1","position":[0.25,0.08,-9.3],"rotation":[0,0,0,-1]},{"name":"lubiao_b2_c020_r5p1","position":[0,0.08,-9.3],"rotation":[0,0,0,-1]},{"name":"lubiao_c2_c020_r5p1","position":[-0.25,0.08,-9.3],"rotation":[0,0,0,-1]},{"name":"Road_05","position":[0,0,-9.3],"rotation":[0,1,0,0]},{"name":"lubiao_a3","position":[0.25,0.07,-9.88],"rotation":[0,0,0,-1]},{"name":"lubiao_b3","position":[0,0.07,-9.88],"rotation":[0,0,0,-1]},{"name":"lubiao_c3","position":[-0.25,0.07,-9.88],"rotation":[0,0,0,-1]},{"name":"lubiao_a4","position":[0.25,-0.39,-10.21],"rotation":[0,0,0,-1]},{"name":"lubiao_c4","position":[-0.25,-0.39,-10.21],"rotation":[0,0,0,-1]},{"name":"lubiao_b4","position":[0,-0.39,-10.21],"rotation":[0,0,0,-1]},{"name":"lubiao_c5","position":[-0.25,-3.21,-11.38],"rotation":[0,0,0,-1]},{"name":"lubiao_b5","position":[0,-3.21,-11.38],"rotation":[0,0,0,-1]},{"name":"lubiao_a5","position":[0.25,-3.21,-11.38],"rotation":[0,0,0,-1]},{"name":"lubiao_a6","position":[0.25,-3.9,-11.96],"rotation":[0,0,0,-1]},{"name":"lubiao_b6","position":[0,-3.9,-11.96],"rotation":[0,0,0,-1]},{"name":"lubiao_c6","position":[-0.25,-3.9,-11.96],"rotation":[0,0,0,-1]},{"name":"lubiao_a7","position":[0.25,-4.2,-12.65],"rotation":[0,0,0,-1]},{"name":"lubiao_b7","position":[0,-4.2,-12.65],"rotation":[0,0,0,-1]},{"name":"lubiao_c7","position":[-0.25,-4.2,-12.65],"rotation":[0,0,0,-1]},{"name":"lubiao_c8","position":[-0.25,-4.25,-13.35],"rotation":[0,0,0,-1]},{"name":"lubiao_b8","position":[0,-4.25,-13.35],"rotation":[0,0,0,-1]},{"name":"lubiao_a8","position":[0.25,-4.25,-13.35],"rotation":[0,0,0,-1]},{"name":"lubiao_c9","position":[-0.25,-3.96,-14.08],"rotation":[0,0,0,-1]},{"name":"lubiao_a9","position":[0.25,-3.96,-14.08],"rotation":[0,0,0,-1]},{"name":"lubiao_b9","position":[0,-3.96,-14.08],"rotation":[0,0,0,-1]},{"name":"lubiao_a10_r5p2","position":[0.25,-3.66,-14.65],"rotation":[0,0,0,-1]},{"name":"lubiao_c10_r5p2","position":[-0.25,-3.66,-14.65],"rotation":[0,0,0,-1]},{"name":"lubiao_b10_r5p2","position":[0,-3.66,-14.65],"rotation":[0,0,0,-1]},{"name":"lubiao_c11","position":[-0.25,-3.57,-15.17],"rotation":[0,0,0,-1]},{"name":"lubiao_b11","position":[0,-3.57,-15.17],"rotation":[0,0,0,-1]},{"name":"lubiao_a11","position":[0.25,-3.57,-15.17],"rotation":[0,0,0,-1]},{"name":"Road_01","position":[0,-4,-15.5],"rotation":[0,0,0,-1]},{"name":"lubiao_c12_cm7_r5p3","position":[-0.25,-4,-15.78],"rotation":[0,0,0,-1]},{"name":"lubiao_a12_cm7_r5p3","position":[0.25,-4,-15.78],"rotation":[0,0,0,-1]},{"name":"lubiao_b12_cm7_r5p3","position":[0,-4,-15.78],"rotation":[0,0,0,-1]},{"name":"Road_01","position":[0,-4,-16],"rotation":[0,0,0,-1]},{"name":"Road_01","position":[0,-4,-16.5],"rotation":[0,0,0,-1]},{"name":"Road_01","position":[0,-4,-17],"rotation":[0,0,0,-1]},{"name":"Road_01","position":[0,-4,-17.5],"rotation":[0,0,0,-1]},{"name":"lubiao_c13_p1","position":[-0.25,-4,-17.79],"rotation":[0,0,0,-1]},{"name":"lubiao_b13_p1","position":[0,-4,-17.79],"rotation":[0,0,0,-1]},{"name":"lubiao_a13_p1","position":[0.25,-4,-17.79],"rotation":[0,0,0,-1]},{"name":"Road_01","position":[0,-4,-18],"rotation":[0,0,0,-1]},{"name":"lubiao_a14_c1","position":[0.25,-4,-18.416],"rotation":[0,0,0,-1]},{"name":"lubiao_c14_c1","position":[-0.25,-4,-18.416],"rotation":[0,0,0,-1]},{"name":"lubiao_b14_c1","position":[0,-4,-18.416],"rotation":[0,0,0,-1]},{"name":"Road_01","position":[0,-4,-18.5],"rotation":[0,0,0,-1]},{"name":"Road_01","position":[0,-4,-19],"rotation":[0,0,0,-1]},{"name":"lubiao_b15_m12p1","position":[0,-4,-19.3],"rotation":[0,0,0,-1]},{"name":"lubiao_c15_m12p1","position":[-0.25,-4,-19.3],"rotation":[0,0,0,-1]},{"name":"lubiao_a15_m12p1","position":[0.25,-4,-19.3],"rotation":[0,0,0,-1]},{"name":"lubiao_a16_m12p2","position":[0.25,-4,-19.5],"rotation":[0,0,0,-1]},{"name":"lubiao_b16_m12p2","position":[0,-4,-19.5],"rotation":[0,0,0,-1]},{"name":"lubiao_c16_m12p2","position":[-0.25,-4,-19.5],"rotation":[0,0,0,-1]},{"name":"Machine_12","position":[0,-2.1,-20.25],"rotation":[0,0,0,-1]},{"name":"Road_01","position":[0,-4,-21],"rotation":[0,0,0,-1]},{"name":"lubiao_b17_m12p3","position":[0,-4,-21.2],"rotation":[0,0,0,-1]},{"name":"lubiao_a17_m12p3","position":[0.25,-4,-21.2],"rotation":[0,0,0,-1]},{"name":"lubiao_c17_m12p3","position":[-0.25,-4,-21.2],"rotation":[0,0,0,-1]},{"name":"Road_01","position":[0,-4,-21.5],"rotation":[0,0,0,-1]},{"name":"Road_01","position":[0,-4,-22],"rotation":[0,0,0,-1]},{"name":"End_01","position":[0,-4,-22.5],"rotation":[0,0,0,-1]},{"name":"lubiao_c18","position":[-0.25,-4,-22.78],"rotation":[0,0,0,-1]},{"name":"lubiao_b18","position":[0,-4,-22.78],"rotation":[0,0,0,-1]},{"name":"lubiao_a18","position":[0.25,-4,-22.78],"rotation":[0,0,0,-1]},{"name":"Road_03","position":[0,-4,-23],"rotation":[0,1,0,0]}]